pelican_data_loader/__init__.py
pelican_data_loader/config.py
pelican_data_loader/data/licenses.jsonl
pelican_data_loader/data.py
pelican_data_loader/db.py
pelican_data_loader/external/person_api.py
pelican_data_loader/utils.py
uwdf-0.0.1.dist-info/licenses/LICENSE
uwdf-0.0.1.dist-info/WHEEL
uwdf-0.0.1.dist-info/METADATA
uwdf-0.0.1.dist-info/RECORD
