Metadata-Version: 2.4
Name: uwdf
Version: 0.0.1
Summary: Pelican Platform backed data loader
License-Expression: MIT
License-File: LICENSE
Requires-Dist: pelicanfs>=1.2.1
Requires-Dist: datasets>=3.6.0
Requires-Dist: httpx>=0.28.1
Requires-Dist: minio>=7.2.15
Requires-Dist: mlcroissant>=1.0.17
Requires-Dist: pandas>=2.2.3
Requires-Dist: pydantic>=2.11.4
Requires-Dist: python-dotenv>=1.1.0
Requires-Dist: datacite>=1.2.0
Requires-Dist: sqlmodel>=0.0.24
Requires-Dist: pydantic-settings>=2.10.1
Requires-Dist: psycopg2-binary>=2.9.10
Requires-Dist: streamlit>=1.46.1
Requires-Python: >=3.12
